tuk/__top__.py
tuk-0.1.0.2025121800.dist-info/licenses/LICENSE
tuk-0.1.0.2025121800.dist-info/METADATA
tuk-0.1.0.2025121800.dist-info/WHEEL
tuk-0.1.0.2025121800.dist-info/top_level.txt
tuk-0.1.0.2025121800.dist-info/RECORD
