Metadata-Version: 2.4
Name: tuk
Version: 0.1.0.2025121800
Summary: Tarcadia's Utility Kit
Home-page: https://github.com/Tarcadia/tuk
Author: Tarcadia
Author-email: dont@email.me
License: MIT
Project-URL: Bug Reports, https://github.com/Tarcadia/tuk/issues
Project-URL: Source, https://github.com/Tarcadia/tuk
Keywords: utility,tuk
Classifier: Development Status :: 2 - Pre-Alpha
Classifier: Intended Audience :: Developers
Classifier: Programming Language :: Python :: 3.11
Classifier: Operating System :: OS Independent
Classifier: Typing :: Typed
Requires-Python: >=3.11
License-File: LICENSE
Requires-Dist: tuk-time==0.1.0
Requires-Dist: tuk-config==0.1.0
Requires-Dist: tuk-logging==0.1.0
Dynamic: author
Dynamic: author-email
Dynamic: classifier
Dynamic: description-content-type
Dynamic: home-page
Dynamic: keywords
Dynamic: license
Dynamic: license-file
Dynamic: project-url
Dynamic: requires-dist
Dynamic: requires-python
Dynamic: summary
